twinning/__init__.py
twinning/twinning.py
twinning/twinning_cpp/twinning_linux_x64.so
twinning/twinning_cpp/twinning_mac_arm.dylib
twinning/twinning_cpp/twinning_mac_x64.dylib
twinning/twinning_cpp/twinning_win_x64.dll
twinning-1.0.1.dist-info/LICENSE
twinning-1.0.1.dist-info/METADATA
twinning-1.0.1.dist-info/WHEEL
twinning-1.0.1.dist-info/top_level.txt
twinning-1.0.1.dist-info/RECORD
